ChETiK/ChETiK.py
ChETiK/__init__.py
ChETiK/__main__.py
ChETiK-0.2.1.dist-info/LICENCE
ChETiK-0.2.1.dist-info/METADATA
ChETiK-0.2.1.dist-info/WHEEL
ChETiK-0.2.1.dist-info/entry_points.txt
ChETiK-0.2.1.dist-info/top_level.txt
ChETiK-0.2.1.dist-info/RECORD
